LICENSE
MANIFEST.in
README.md
pyproject.toml
setup.cfg
setup.py
csrc/lap_torch.cu
csrc/LAP/Hung_lap.cuh
csrc/LAP/device_utils.cuh
csrc/LAP/lap_kernels.cuh
csrc/include/Timer.h
csrc/include/defs.cuh
csrc/include/logger.cuh
csrc/include/utils.cuh
figs/benchmark_integer.png
figs/benchmark_normal.png
figs/benchmark_uniform.png
torch_lap_cuda/__init__.py
torch_lap_cuda/lap.py
torch_lap_cuda.egg-info/PKG-INFO
torch_lap_cuda.egg-info/SOURCES.txt
torch_lap_cuda.egg-info/dependency_links.txt
torch_lap_cuda.egg-info/not-zip-safe
torch_lap_cuda.egg-info/requires.txt
torch_lap_cuda.egg-info/top_level.txt