Metadata-Version: 2.1
Name: torch-lap-cuda
Version: 0.0.3
Summary: PyTorch wrapper for HyLAC CUDA library for solving linear assignment problems.
Home-page: https://github.com/dkobylianskii/torch-lap-cuda
Author: Dmitrii Kobylianskii, Clinton Ansun Mo
Author-email: Dmitrii Kobylianskii <kobad2@gmail.com>, Clinton Ansun Mo <clinton.mo@weblab.t.u-tokyo.ac.jp>
License: MIT License
Project-URL: Homepage, https://github.com/dkobylianskii/torch-lap-cuda
Project-URL: Issues, https://github.com/dkobylianskii/torch-lap-cuda/issues
Keywords: machine learning,linear assignment problem,lap,cuda,torch
Classifier: Programming Language :: Python :: 3
Classifier: Operating System :: OS Independent
Requires-Python: >=3.9
License-File: LICENSE
